immunity_notifications/CONTRIBUTING.rst
immunity_notifications/__init__.py
immunity_notifications/admin.py
immunity_notifications/apps.py
immunity_notifications/checks.py
immunity_notifications/context_processors.py
immunity_notifications/exceptions.py
immunity_notifications/handlers.py
immunity_notifications/models.py
immunity_notifications/settings.py
immunity_notifications/signals.py
immunity_notifications/swapper.py
immunity_notifications/tasks.py
immunity_notifications/types.py
immunity_notifications/urls.py
immunity_notifications/utils.py
immunity_notifications/widgets.py
immunity_notifications/api/__init__.py
immunity_notifications/api/filters.py
immunity_notifications/api/serializers.py
immunity_notifications/api/urls.py
immunity_notifications/api/views.py
immunity_notifications/base/__init__.py
immunity_notifications/base/admin.py
immunity_notifications/base/forms.py
immunity_notifications/base/models.py
immunity_notifications/management/__init__.py
immunity_notifications/management/commands/__init__.py
immunity_notifications/management/commands/create_notification.py
immunity_notifications/management/commands/populate_notification_preferences.py
immunity_notifications/migrations/__init__.py
immunity_notifications/static/openwisp-notifications/audio/notification_bell.mp3
immunity_notifications/static/openwisp-notifications/css/loader.css
immunity_notifications/static/openwisp-notifications/css/notifications.css
immunity_notifications/static/openwisp-notifications/css/object-notifications.css
immunity_notifications/static/openwisp-notifications/images/icons/icon-bell-slash.svg
immunity_notifications/static/openwisp-notifications/images/icons/icon-bell.svg
immunity_notifications/static/openwisp-notifications/images/icons/icon-close.svg
immunity_notifications/static/openwisp-notifications/images/icons/icon-error.svg
immunity_notifications/static/openwisp-notifications/images/icons/icon-info.svg
immunity_notifications-1.1.dist-info/LICENSE
immunity_notifications-1.1.dist-info/METADATA
immunity_notifications-1.1.dist-info/WHEEL
immunity_notifications-1.1.dist-info/top_level.txt
immunity_notifications-1.1.dist-info/RECORD
