Metadata-Version: 2.1
Name: immunity-notifications
Version: 1.1
Summary: Notifications module of OpenWISP
Home-page: http://openwisp.org
Author: OpenWISP
Author-email: support@openwisp.io
License: GPL3
Download-URL: https://github.com/edge-servers/immunity-notifications/releases
Keywords: django,netjson,notification,openwisp,monitoring
Platform: Platform Independent
Classifier: Development Status :: 5 - Production/Stable
Classifier: Environment :: Web Environment
Classifier: Topic :: Internet :: WWW/HTTP
Classifier: Topic :: System :: Networking
Classifier: Intended Audience :: Developers
Classifier: License :: OSI Approved :: GNU General Public License v3 (GPLv3)
Classifier: Operating System :: OS Independent
Classifier: Framework :: Django
Classifier: Programming Language :: Python :: 3.8
License-File: LICENSE
Requires-Dist: channels~=3.0.2
Requires-Dist: django-notifications-hq~=1.8.3
Requires-Dist: immunity-users~=1.1
Requires-Dist: markdown~=3.7.0
Requires-Dist: openwisp-utils[celery,rest]~=1.1.0
